config.py
kria_cross_comp.py
movex.py
movex-1.1.dist-info/licenses/LICENSE
movex-1.1.dist-info/METADATA
movex-1.1.dist-info/WHEEL
movex-1.1.dist-info/entry_points.txt
movex-1.1.dist-info/top_level.txt
movex-1.1.dist-info/RECORD
