Metadata-Version: 2.4
Name: movex
Version: 1.1
Summary: A command-line tool to deal with Kria's clumsiness.
Author: MMR E-Driverless Team
Project-URL: Homepage, https://github.com/MMR-Electric-Driverless/movex
Project-URL: Issues, https://github.com/MMR-Electric-Driverless/movex/issues
Requires-Python: >=3.12
License-File: LICENSE
Requires-Dist: docker>=7.1.0
Requires-Dist: simple-term-menu>=1.6.6
Dynamic: license-file
